{"version":{"fullVersion":"2.0.6","major":"2","minor":"0","patch":"6"},"meta":{"flags":["experimentalData"]},"collections":[{"name":"homePage","label":"🏠 Startseite","path":"content/home","format":"json","match":{"include":"startseite"},"ui":{"global":true,"allowedActions":{"create":false,"delete":false}},"fields":[{"type":"object","name":"seo","label":"🔍 SEO & Google","fields":[{"type":"string","name":"title","label":"Browser-Titel","required":true,"description":"Titel im Browser-Tab","namespace":["homePage","seo","title"],"searchable":true,"uid":false},{"type":"string","name":"description","label":"Suchbeschreibung","ui":{"component":"textarea"},"description":"Text in Google-Ergebnissen","namespace":["homePage","seo","description"],"searchable":true,"uid":false},{"type":"image","name":"ogImage","label":"Social Media Bild","description":"Bild für Facebook/Twitter Vorschau","namespace":["homePage","seo","ogImage"],"searchable":false,"uid":false}],"namespace":["homePage","seo"],"searchable":true,"uid":false},{"type":"object","name":"hero","label":"👋 Oberer Bereich (Intro)","fields":[{"type":"string","name":"eyebrow","label":"Kleine Überschrift","description":"z.B. \"MEISTERBETRIEB\"","namespace":["homePage","hero","eyebrow"],"searchable":true,"uid":false},{"type":"string","name":"title","label":"Haupttitel (H1)","required":true,"namespace":["homePage","hero","title"],"searchable":true,"uid":false},{"type":"string","name":"subtitle","label":"Untertitel","namespace":["homePage","hero","subtitle"],"searchable":true,"uid":false},{"type":"string","name":"description","label":"Einleitungstext","ui":{"component":"textarea"},"namespace":["homePage","hero","description"],"searchable":true,"uid":false},{"type":"object","name":"buttons","label":"Buttons","fields":[{"type":"string","name":"primaryText","label":"Haupt-Button Text","namespace":["homePage","hero","buttons","primaryText"],"searchable":true,"uid":false},{"type":"string","name":"primaryLink","label":"Haupt-Button Link","namespace":["homePage","hero","buttons","primaryLink"],"searchable":true,"uid":false},{"type":"string","name":"secondaryText","label":"Zweit-Button Text","namespace":["homePage","hero","buttons","secondaryText"],"searchable":true,"uid":false},{"type":"string","name":"secondaryLink","label":"Zweit-Button Link","namespace":["homePage","hero","buttons","secondaryLink"],"searchable":true,"uid":false}],"namespace":["homePage","hero","buttons"],"searchable":true,"uid":false},{"type":"image","name":"backgroundImage","label":"Hintergrundbild","namespace":["homePage","hero","backgroundImage"],"searchable":false,"uid":false},{"type":"string","name":"videoUrl","label":"Video URL","namespace":["homePage","hero","videoUrl"],"searchable":true,"uid":false},{"type":"boolean","name":"showQuickForm","label":"Kontaktformular anzeigen?","namespace":["homePage","hero","showQuickForm"],"searchable":true,"uid":false}],"namespace":["homePage","hero"],"searchable":true,"uid":false},{"type":"object","name":"quickForm","label":"⚡ Schnellanfrage-Box","fields":[{"type":"string","name":"title","label":"Titel","required":true,"namespace":["homePage","quickForm","title"],"searchable":true,"uid":false},{"type":"string","name":"nameLabel","label":"Platzhalter Name","namespace":["homePage","quickForm","nameLabel"],"searchable":true,"uid":false},{"type":"string","name":"contactLabel","label":"Platzhalter Kontakt","namespace":["homePage","quickForm","contactLabel"],"searchable":true,"uid":false},{"type":"string","name":"buttonText","label":"Button Text","namespace":["homePage","quickForm","buttonText"],"searchable":true,"uid":false},{"type":"string","name":"disclaimer","label":"Hinweistext","namespace":["homePage","quickForm","disclaimer"],"searchable":true,"uid":false}],"namespace":["homePage","quickForm"],"searchable":true,"uid":false},{"type":"object","list":true,"name":"stats","label":"📊 Statistiken (Zahlen)","ui":{"max":6},"fields":[{"type":"string","name":"value","label":"Zahl (z.B. 28)","required":true,"namespace":["homePage","stats","value"],"searchable":true,"uid":false},{"type":"string","name":"label","label":"Einheit (z.B. Experten)","required":true,"namespace":["homePage","stats","label"],"searchable":true,"uid":false},{"type":"string","name":"icon","label":"Icon Name (Englisch)","namespace":["homePage","stats","icon"],"searchable":true,"uid":false}],"namespace":["homePage","stats"],"searchable":true,"uid":false},{"type":"object","name":"servicesSection","label":"🛠️ Leistungen (Vorschau)","fields":[{"type":"string","name":"eyebrow","label":"Kleine Überschrift","namespace":["homePage","servicesSection","eyebrow"],"searchable":true,"uid":false},{"type":"string","name":"title","label":"Titel","namespace":["homePage","servicesSection","title"],"searchable":true,"uid":false},{"type":"string","name":"description","label":"Text","ui":{"component":"textarea"},"namespace":["homePage","servicesSection","description"],"searchable":true,"uid":false},{"type":"object","list":true,"name":"services","label":"Leistungen","ui":{"max":8},"fields":[{"type":"string","name":"title","label":"Titel","required":true,"namespace":["homePage","servicesSection","services","title"],"searchable":true,"uid":false},{"type":"string","name":"description","label":"Beschreibung","ui":{"component":"textarea"},"required":true,"namespace":["homePage","servicesSection","services","description"],"searchable":true,"uid":false},{"type":"image","name":"image","label":"Bild","required":true,"namespace":["homePage","servicesSection","services","image"],"searchable":false,"uid":false},{"type":"string","name":"icon","label":"Icon (Lucide)","description":"z.B. Home, Layers, Zap, Sun, Hammer","namespace":["homePage","servicesSection","services","icon"],"searchable":true,"uid":false},{"type":"string","list":true,"name":"checkpoints","label":"Stichpunkte","description":"Wichtige Merkmale als Liste","namespace":["homePage","servicesSection","services","checkpoints"],"searchable":true,"uid":false},{"type":"string","name":"ctaText","label":"Button Text","namespace":["homePage","servicesSection","services","ctaText"],"searchable":true,"uid":false},{"type":"string","name":"link","label":"Link","description":"z.B. /de/services/steildach","namespace":["homePage","servicesSection","services","link"],"searchable":true,"uid":false}],"namespace":["homePage","servicesSection","services"],"searchable":true,"uid":false}],"namespace":["homePage","servicesSection"],"searchable":true,"uid":false},{"type":"object","name":"ceoQuote","label":"💬 Zitat / Über Uns","fields":[{"type":"string","name":"eyebrow","label":"Kleine Überschrift","namespace":["homePage","ceoQuote","eyebrow"],"searchable":true,"uid":false},{"type":"string","name":"name","label":"Name","required":true,"namespace":["homePage","ceoQuote","name"],"searchable":true,"uid":false},{"type":"string","name":"role","label":"Position","required":true,"namespace":["homePage","ceoQuote","role"],"searchable":true,"uid":false},{"type":"string","name":"quote","label":"Zitat (Groß)","ui":{"component":"textarea"},"required":true,"namespace":["homePage","ceoQuote","quote"],"searchable":true,"uid":false},{"type":"string","name":"text","label":"Fließtext","ui":{"component":"textarea"},"namespace":["homePage","ceoQuote","text"],"searchable":true,"uid":false},{"type":"image","name":"image","label":"Foto","namespace":["homePage","ceoQuote","image"],"searchable":false,"uid":false},{"type":"string","name":"buttonText","label":"Button Text","namespace":["homePage","ceoQuote","buttonText"],"searchable":true,"uid":false},{"type":"string","name":"buttonLink","label":"Button Link","namespace":["homePage","ceoQuote","buttonLink"],"searchable":true,"uid":false}],"namespace":["homePage","ceoQuote"],"searchable":true,"uid":false},{"type":"object","name":"projectsSection","label":"🏗️ Projekte & Referenzen","fields":[{"type":"string","name":"eyebrow","label":"Kleine Überschrift","namespace":["homePage","projectsSection","eyebrow"],"searchable":true,"uid":false},{"type":"string","name":"title","label":"Titel","namespace":["homePage","projectsSection","title"],"searchable":true,"uid":false},{"type":"object","list":true,"name":"items","label":"Projekte","ui":{"max":6},"fields":[{"type":"string","name":"title","label":"Projektname","required":true,"namespace":["homePage","projectsSection","items","title"],"searchable":true,"uid":false},{"type":"string","name":"description","label":"Art der Arbeit","namespace":["homePage","projectsSection","items","description"],"searchable":true,"uid":false},{"type":"image","name":"image","label":"Bild","required":true,"namespace":["homePage","projectsSection","items","image"],"searchable":false,"uid":false}],"namespace":["homePage","projectsSection","items"],"searchable":true,"uid":false}],"namespace":["homePage","projectsSection"],"searchable":true,"uid":false},{"type":"object","name":"trustIndicators","label":"🤝 Vertrauens-Elemente","fields":[{"type":"string","name":"eyebrow","label":"Kleine Überschrift","namespace":["homePage","trustIndicators","eyebrow"],"searchable":true,"uid":false},{"type":"string","name":"title","label":"Titel","required":true,"namespace":["homePage","trustIndicators","title"],"searchable":true,"uid":false},{"type":"string","name":"description","label":"Text","ui":{"component":"textarea"},"namespace":["homePage","trustIndicators","description"],"searchable":true,"uid":false},{"type":"image","name":"image","label":"Bild","namespace":["homePage","trustIndicators","image"],"searchable":false,"uid":false},{"type":"object","list":true,"name":"items","label":"Listenpunkte","ui":{"max":4},"fields":[{"type":"string","name":"title","label":"Titel","required":true,"namespace":["homePage","trustIndicators","items","title"],"searchable":true,"uid":false},{"type":"string","name":"description","label":"Text","namespace":["homePage","trustIndicators","items","description"],"searchable":true,"uid":false},{"type":"string","name":"icon","label":"Icon (Lucide)","namespace":["homePage","trustIndicators","items","icon"],"searchable":true,"uid":false}],"namespace":["homePage","trustIndicators","items"],"searchable":true,"uid":false}],"namespace":["homePage","trustIndicators"],"searchable":true,"uid":false},{"type":"object","name":"faqSection","label":"❓ Häufige Fragen (FAQ)","fields":[{"type":"string","name":"title","label":"Titel","namespace":["homePage","faqSection","title"],"searchable":true,"uid":false},{"type":"string","name":"description","label":"Text","namespace":["homePage","faqSection","description"],"searchable":true,"uid":false},{"type":"object","list":true,"name":"questions","label":"Fragen","ui":{"max":10},"fields":[{"type":"string","name":"question","label":"Frage","required":true,"namespace":["homePage","faqSection","questions","question"],"searchable":true,"uid":false},{"type":"string","name":"answer","label":"Antwort","ui":{"component":"textarea"},"required":true,"namespace":["homePage","faqSection","questions","answer"],"searchable":true,"uid":false}],"namespace":["homePage","faqSection","questions"],"searchable":true,"uid":false},{"type":"object","name":"cta","label":"Kontaktbox (unter FAQ)","fields":[{"type":"string","name":"title","label":"Titel","namespace":["homePage","faqSection","cta","title"],"searchable":true,"uid":false},{"type":"string","name":"description","label":"Text","namespace":["homePage","faqSection","cta","description"],"searchable":true,"uid":false},{"type":"string","name":"phone","label":"Telefon","namespace":["homePage","faqSection","cta","phone"],"searchable":true,"uid":false},{"type":"string","name":"buttonText","label":"Button Text","namespace":["homePage","faqSection","cta","buttonText"],"searchable":true,"uid":false},{"type":"string","name":"buttonLink","label":"Link","namespace":["homePage","faqSection","cta","buttonLink"],"searchable":true,"uid":false}],"namespace":["homePage","faqSection","cta"],"searchable":true,"uid":false}],"namespace":["homePage","faqSection"],"searchable":true,"uid":false},{"type":"object","name":"finalCTA","label":"📣 Abschluss-Bereich","fields":[{"type":"string","name":"title","label":"Titel","required":true,"namespace":["homePage","finalCTA","title"],"searchable":true,"uid":false},{"type":"string","name":"description","label":"Text","ui":{"component":"textarea"},"namespace":["homePage","finalCTA","description"],"searchable":true,"uid":false},{"type":"string","name":"buttonText","label":"Button Text","namespace":["homePage","finalCTA","buttonText"],"searchable":true,"uid":false},{"type":"string","name":"buttonLink","label":"Button Link","namespace":["homePage","finalCTA","buttonLink"],"searchable":true,"uid":false}],"namespace":["homePage","finalCTA"],"searchable":true,"uid":false}],"namespace":["homePage"]},{"name":"aboutPage","label":"📄 Über Uns","path":"content/about","format":"json","match":{"include":"about"},"ui":{"global":true,"allowedActions":{"create":false,"delete":false}},"fields":[{"type":"object","name":"seo","label":"🔍 SEO & Google","fields":[{"type":"string","name":"title","label":"Browser-Titel","required":true,"description":"Titel im Browser-Tab","namespace":["aboutPage","seo","title"],"searchable":true,"uid":false},{"type":"string","name":"description","label":"Suchbeschreibung","ui":{"component":"textarea"},"description":"Text in Google-Ergebnissen","namespace":["aboutPage","seo","description"],"searchable":true,"uid":false},{"type":"image","name":"ogImage","label":"Social Media Bild","description":"Bild für Facebook/Twitter Vorschau","namespace":["aboutPage","seo","ogImage"],"searchable":false,"uid":false}],"namespace":["aboutPage","seo"],"searchable":true,"uid":false},{"type":"object","name":"hero","label":"👋 Hero Bereich","fields":[{"type":"string","name":"eyebrow","label":"Kleine Überschrift","namespace":["aboutPage","hero","eyebrow"],"searchable":true,"uid":false},{"type":"string","name":"title","label":"Haupttitel (H1)","required":true,"namespace":["aboutPage","hero","title"],"searchable":true,"uid":false},{"type":"string","name":"description","label":"Beschreibung","ui":{"component":"textarea"},"namespace":["aboutPage","hero","description"],"searchable":true,"uid":false}],"namespace":["aboutPage","hero"],"searchable":true,"uid":false},{"type":"object","name":"story","label":"📖 Geschichte","fields":[{"type":"string","name":"title","label":"Titel","namespace":["aboutPage","story","title"],"searchable":true,"uid":false},{"type":"string","name":"text1","label":"Absatz 1","ui":{"component":"textarea"},"namespace":["aboutPage","story","text1"],"searchable":true,"uid":false},{"type":"string","name":"text2","label":"Absatz 2","ui":{"component":"textarea"},"namespace":["aboutPage","story","text2"],"searchable":true,"uid":false},{"type":"image","name":"image","label":"Bild","namespace":["aboutPage","story","image"],"searchable":false,"uid":false}],"namespace":["aboutPage","story"],"searchable":true,"uid":false},{"type":"object","list":true,"name":"values","label":"✅ Werte / Highlights","ui":{"max":6},"fields":[{"type":"string","name":"text","label":"Text","required":true,"namespace":["aboutPage","values","text"],"searchable":true,"uid":false},{"type":"string","name":"icon","label":"Icon (Lucide)","namespace":["aboutPage","values","icon"],"searchable":true,"uid":false}],"namespace":["aboutPage","values"],"searchable":true,"uid":false},{"type":"object","name":"equipment","label":"🔧 Ausstattung","fields":[{"type":"string","name":"title","label":"Titel","namespace":["aboutPage","equipment","title"],"searchable":true,"uid":false},{"type":"string","name":"description","label":"Beschreibung","ui":{"component":"textarea"},"namespace":["aboutPage","equipment","description"],"searchable":true,"uid":false}],"namespace":["aboutPage","equipment"],"searchable":true,"uid":false},{"type":"object","name":"teamSection","label":"👥 Team Bereich","fields":[{"type":"string","name":"title","label":"Titel","namespace":["aboutPage","teamSection","title"],"searchable":true,"uid":false},{"type":"string","name":"description","label":"Beschreibung","ui":{"component":"textarea"},"namespace":["aboutPage","teamSection","description"],"searchable":true,"uid":false}],"namespace":["aboutPage","teamSection"],"searchable":true,"uid":false},{"type":"object","name":"cta","label":"📣 Call-to-Action","fields":[{"type":"string","name":"title","label":"Titel","namespace":["aboutPage","cta","title"],"searchable":true,"uid":false},{"type":"string","name":"description","label":"Beschreibung","ui":{"component":"textarea"},"namespace":["aboutPage","cta","description"],"searchable":true,"uid":false},{"type":"string","name":"buttonText","label":"Button Text","namespace":["aboutPage","cta","buttonText"],"searchable":true,"uid":false},{"type":"string","name":"email","label":"E-Mail","namespace":["aboutPage","cta","email"],"searchable":true,"uid":false}],"namespace":["aboutPage","cta"],"searchable":true,"uid":false}],"namespace":["aboutPage"]},{"name":"careerPage","label":"💼 Karriere","path":"content/career","format":"json","match":{"include":"career"},"ui":{"global":true,"allowedActions":{"create":false,"delete":false}},"fields":[{"type":"object","name":"seo","label":"🔍 SEO & Google","fields":[{"type":"string","name":"title","label":"Browser-Titel","required":true,"description":"Titel im Browser-Tab","namespace":["careerPage","seo","title"],"searchable":true,"uid":false},{"type":"string","name":"description","label":"Suchbeschreibung","ui":{"component":"textarea"},"description":"Text in Google-Ergebnissen","namespace":["careerPage","seo","description"],"searchable":true,"uid":false},{"type":"image","name":"ogImage","label":"Social Media Bild","description":"Bild für Facebook/Twitter Vorschau","namespace":["careerPage","seo","ogImage"],"searchable":false,"uid":false}],"namespace":["careerPage","seo"],"searchable":true,"uid":false},{"type":"object","name":"hero","label":"👋 Hero Bereich","fields":[{"type":"string","name":"eyebrow","label":"Kleine Überschrift","namespace":["careerPage","hero","eyebrow"],"searchable":true,"uid":false},{"type":"string","name":"title","label":"Haupttitel (H1)","required":true,"namespace":["careerPage","hero","title"],"searchable":true,"uid":false},{"type":"string","name":"description","label":"Beschreibung","ui":{"component":"textarea"},"namespace":["careerPage","hero","description"],"searchable":true,"uid":false},{"type":"image","name":"backgroundImage","label":"Hintergrundbild","namespace":["careerPage","hero","backgroundImage"],"searchable":false,"uid":false}],"namespace":["careerPage","hero"],"searchable":true,"uid":false},{"type":"object","name":"jobsSection","label":"💼 Stellenangebote Bereich","fields":[{"type":"string","name":"title","label":"Titel","namespace":["careerPage","jobsSection","title"],"searchable":true,"uid":false},{"type":"string","name":"emptyMessage","label":"Text wenn keine Stellen","namespace":["careerPage","jobsSection","emptyMessage"],"searchable":true,"uid":false}],"namespace":["careerPage","jobsSection"],"searchable":true,"uid":false},{"type":"object","name":"wizardSection","label":"🧙 Karriere Finder","fields":[{"type":"string","name":"title","label":"Titel","namespace":["careerPage","wizardSection","title"],"searchable":true,"uid":false},{"type":"string","name":"description","label":"Beschreibung","ui":{"component":"textarea"},"namespace":["careerPage","wizardSection","description"],"searchable":true,"uid":false}],"namespace":["careerPage","wizardSection"],"searchable":true,"uid":false}],"namespace":["careerPage"]},{"name":"contactPage","label":"📬 Kontakt","path":"content/contact","format":"json","match":{"include":"contact"},"ui":{"global":true,"allowedActions":{"create":false,"delete":false}},"fields":[{"type":"object","name":"seo","label":"🔍 SEO & Google","fields":[{"type":"string","name":"title","label":"Browser-Titel","required":true,"description":"Titel im Browser-Tab","namespace":["contactPage","seo","title"],"searchable":true,"uid":false},{"type":"string","name":"description","label":"Suchbeschreibung","ui":{"component":"textarea"},"description":"Text in Google-Ergebnissen","namespace":["contactPage","seo","description"],"searchable":true,"uid":false},{"type":"image","name":"ogImage","label":"Social Media Bild","description":"Bild für Facebook/Twitter Vorschau","namespace":["contactPage","seo","ogImage"],"searchable":false,"uid":false}],"namespace":["contactPage","seo"],"searchable":true,"uid":false},{"type":"string","name":"title","label":"Seitentitel","namespace":["contactPage","title"],"searchable":true,"uid":false},{"type":"string","name":"description","label":"Beschreibung","ui":{"component":"textarea"},"namespace":["contactPage","description"],"searchable":true,"uid":false},{"type":"object","name":"address","label":"📍 Adresse","fields":[{"type":"string","name":"company","label":"Firmenname","required":true,"namespace":["contactPage","address","company"],"searchable":true,"uid":false},{"type":"string","name":"street","label":"Straße","required":true,"namespace":["contactPage","address","street"],"searchable":true,"uid":false},{"type":"string","name":"city","label":"Stadt","required":true,"namespace":["contactPage","address","city"],"searchable":true,"uid":false},{"type":"string","name":"zip","label":"PLZ","required":true,"namespace":["contactPage","address","zip"],"searchable":true,"uid":false}],"namespace":["contactPage","address"],"searchable":true,"uid":false},{"type":"string","name":"phone","label":"Telefon","required":true,"namespace":["contactPage","phone"],"searchable":true,"uid":false},{"type":"string","name":"fax","label":"Fax","namespace":["contactPage","fax"],"searchable":true,"uid":false},{"type":"string","name":"email","label":"E-Mail","required":true,"namespace":["contactPage","email"],"searchable":true,"uid":false},{"type":"string","name":"website","label":"Website","namespace":["contactPage","website"],"searchable":true,"uid":false},{"type":"string","name":"facebook","label":"Facebook URL","namespace":["contactPage","facebook"],"searchable":true,"uid":false},{"type":"object","name":"officeHours","label":"🕐 Öffnungszeiten Büro","fields":[{"type":"string","name":"weekdays","label":"Mo-Fr Text","required":true,"namespace":["contactPage","officeHours","weekdays"],"searchable":true,"uid":false}],"namespace":["contactPage","officeHours"],"searchable":true,"uid":false},{"type":"object","name":"repairHours","label":"🔧 Reparaturplanung Zeiten","fields":[{"type":"string","name":"tueThu","label":"Di-Do Text","required":true,"namespace":["contactPage","repairHours","tueThu"],"searchable":true,"uid":false},{"type":"string","name":"fri","label":"Fr Text","required":true,"namespace":["contactPage","repairHours","fri"],"searchable":true,"uid":false}],"namespace":["contactPage","repairHours"],"searchable":true,"uid":false}],"namespace":["contactPage"]},{"name":"page","label":"➕ Weitere Seiten","path":"content/pages","format":"json","ui":{},"fields":[{"type":"string","name":"title","label":"Seitentitel (intern)","required":true,"isTitle":true,"namespace":["page","title"],"searchable":true,"uid":false},{"type":"string","name":"slug","label":"URL-Pfad","required":true,"description":"z.B. \"about\" für /de/about","namespace":["page","slug"],"searchable":true,"uid":false},{"type":"object","name":"seo","label":"🔍 SEO & Google","fields":[{"type":"string","name":"title","label":"Browser-Titel","required":true,"description":"Titel im Browser-Tab","namespace":["page","seo","title"],"searchable":true,"uid":false},{"type":"string","name":"description","label":"Suchbeschreibung","ui":{"component":"textarea"},"description":"Text in Google-Ergebnissen","namespace":["page","seo","description"],"searchable":true,"uid":false},{"type":"image","name":"ogImage","label":"Social Media Bild","description":"Bild für Facebook/Twitter Vorschau","namespace":["page","seo","ogImage"],"searchable":false,"uid":false}],"namespace":["page","seo"],"searchable":true,"uid":false},{"type":"object","list":true,"name":"blocks","label":"🧱 Seiteninhalt (Blöcke)","templates":[{"name":"hero","label":"👋 Hero Banner","fields":[{"type":"string","name":"eyebrow","label":"Kleine Überschrift","description":"z.B. \"MEISTERBETRIEB\"","namespace":["page","blocks","hero","eyebrow"],"searchable":true,"uid":false},{"type":"string","name":"title","label":"Haupttitel (H1)","namespace":["page","blocks","hero","title"],"searchable":true,"uid":false},{"type":"string","name":"subtitle","label":"Untertitel","namespace":["page","blocks","hero","subtitle"],"searchable":true,"uid":false},{"type":"string","name":"description","label":"Einleitungstext","ui":{"component":"textarea"},"namespace":["page","blocks","hero","description"],"searchable":true,"uid":false},{"type":"object","name":"primaryButton","label":"Haupt-Button","fields":[{"type":"string","name":"text","label":"Button Text","required":true,"namespace":["page","blocks","hero","primaryButton","text"]},{"type":"string","name":"link","label":"Link","required":true,"namespace":["page","blocks","hero","primaryButton","link"]},{"type":"string","name":"variant","label":"Stil","options":[{"label":"Primär","value":"primary"},{"label":"Sekundär","value":"secondary"},{"label":"Outline","value":"outline"}],"namespace":["page","blocks","hero","primaryButton","variant"]}],"namespace":["page","blocks","hero","primaryButton"],"searchable":true,"uid":false},{"type":"object","name":"secondaryButton","label":"Zweit-Button","fields":[{"type":"string","name":"text","label":"Button Text","required":true,"namespace":["page","blocks","hero","secondaryButton","text"]},{"type":"string","name":"link","label":"Link","required":true,"namespace":["page","blocks","hero","secondaryButton","link"]},{"type":"string","name":"variant","label":"Stil","options":[{"label":"Primär","value":"primary"},{"label":"Sekundär","value":"secondary"},{"label":"Outline","value":"outline"}],"namespace":["page","blocks","hero","secondaryButton","variant"]}],"namespace":["page","blocks","hero","secondaryButton"],"searchable":true,"uid":false},{"type":"image","name":"backgroundImage","label":"Hintergrundbild","namespace":["page","blocks","hero","backgroundImage"],"searchable":false,"uid":false},{"type":"string","name":"variant","label":"Stil Variante","options":[{"label":"Standard (dunkel)","value":"dark"},{"label":"Hell","value":"light"},{"label":"Mit Überlagerung","value":"overlay"}],"namespace":["page","blocks","hero","variant"],"searchable":true,"uid":false}],"namespace":["page","blocks","hero"]},{"name":"content","label":"📝 Text/Inhalt","fields":[{"type":"string","name":"eyebrow","label":"Kleine Überschrift","namespace":["page","blocks","content","eyebrow"],"searchable":true,"uid":false},{"type":"string","name":"title","label":"Titel","namespace":["page","blocks","content","title"],"searchable":true,"uid":false},{"type":"rich-text","name":"body","label":"Inhalt","namespace":["page","blocks","content","body"],"searchable":true,"parser":{"type":"markdown"},"uid":false},{"type":"image","name":"image","label":"Bild (optional)","namespace":["page","blocks","content","image"],"searchable":false,"uid":false},{"type":"string","name":"imagePosition","label":"Bild Position","options":[{"label":"Links","value":"left"},{"label":"Rechts","value":"right"},{"label":"Oben","value":"top"},{"label":"Unten","value":"bottom"}],"namespace":["page","blocks","content","imagePosition"],"searchable":true,"uid":false}],"namespace":["page","blocks","content"]},{"name":"story","label":"📖 Geschichte/Story","fields":[{"type":"string","name":"title","label":"Titel","namespace":["page","blocks","story","title"],"searchable":true,"uid":false},{"type":"string","name":"text1","label":"Absatz 1","ui":{"component":"textarea"},"namespace":["page","blocks","story","text1"],"searchable":true,"uid":false},{"type":"string","name":"text2","label":"Absatz 2","ui":{"component":"textarea"},"namespace":["page","blocks","story","text2"],"searchable":true,"uid":false},{"type":"image","name":"image","label":"Bild","namespace":["page","blocks","story","image"],"searchable":false,"uid":false},{"type":"object","list":true,"name":"highlights","label":"Highlights/Werte","ui":{"max":6},"fields":[{"type":"string","name":"text","label":"Text","required":true,"namespace":["page","blocks","story","highlights","text"]},{"type":"string","name":"icon","label":"Icon (Lucide)","namespace":["page","blocks","story","highlights","icon"]}],"namespace":["page","blocks","story","highlights"],"searchable":true,"uid":false}],"namespace":["page","blocks","story"]},{"name":"features","label":"⭐ Features/Merkmale","fields":[{"type":"string","name":"eyebrow","label":"Kleine Überschrift","namespace":["page","blocks","features","eyebrow"],"searchable":true,"uid":false},{"type":"string","name":"title","label":"Titel","namespace":["page","blocks","features","title"],"searchable":true,"uid":false},{"type":"string","name":"description","label":"Beschreibung","ui":{"component":"textarea"},"namespace":["page","blocks","features","description"],"searchable":true,"uid":false},{"type":"object","list":true,"name":"items","label":"Features","ui":{"max":8},"fields":[{"type":"string","name":"icon","label":"Icon (Lucide)","description":"z.B. CheckCircle, Star, Shield","namespace":["page","blocks","features","items","icon"]},{"type":"string","name":"title","label":"Titel","required":true,"namespace":["page","blocks","features","items","title"]},{"type":"string","name":"description","label":"Beschreibung","ui":{"component":"textarea"},"namespace":["page","blocks","features","items","description"]}],"namespace":["page","blocks","features","items"],"searchable":true,"uid":false},{"type":"string","name":"columns","label":"Spalten","options":[{"label":"2 Spalten","value":"2"},{"label":"3 Spalten","value":"3"},{"label":"4 Spalten","value":"4"}],"namespace":["page","blocks","features","columns"],"searchable":true,"uid":false}],"namespace":["page","blocks","features"]},{"name":"equipment","label":"🔧 Ausstattung/Info","fields":[{"type":"string","name":"icon","label":"Icon (Lucide)","description":"z.B. Hammer, Wrench, Truck","namespace":["page","blocks","equipment","icon"],"searchable":true,"uid":false},{"type":"string","name":"title","label":"Titel","namespace":["page","blocks","equipment","title"],"searchable":true,"uid":false},{"type":"string","name":"description","label":"Beschreibung","ui":{"component":"textarea"},"namespace":["page","blocks","equipment","description"],"searchable":true,"uid":false}],"namespace":["page","blocks","equipment"]},{"name":"teamGrid","label":"👥 Team Übersicht","fields":[{"type":"string","name":"title","label":"Titel","namespace":["page","blocks","teamGrid","title"],"searchable":true,"uid":false},{"type":"string","name":"description","label":"Beschreibung","ui":{"component":"textarea"},"namespace":["page","blocks","teamGrid","description"],"searchable":true,"uid":false},{"type":"string","name":"categories","label":"Angezeigte Kategorien","list":true,"options":[{"label":"Geschäftsführung","value":"leadership"},{"label":"Büro","value":"office"},{"label":"Dachdecker","value":"craftsmen"}],"namespace":["page","blocks","teamGrid","categories"],"searchable":true,"uid":false},{"type":"boolean","name":"showEmail","label":"E-Mails anzeigen?","namespace":["page","blocks","teamGrid","showEmail"],"searchable":true,"uid":false}],"namespace":["page","blocks","teamGrid"]},{"name":"jobsList","label":"💼 Stellenangebote","fields":[{"type":"string","name":"title","label":"Titel","namespace":["page","blocks","jobsList","title"],"searchable":true,"uid":false},{"type":"string","name":"emptyMessage","label":"Text wenn keine Stellen","namespace":["page","blocks","jobsList","emptyMessage"],"searchable":true,"uid":false}],"namespace":["page","blocks","jobsList"]},{"name":"form","label":"📋 Kontaktformular","fields":[{"type":"string","name":"title","label":"Titel","namespace":["page","blocks","form","title"],"searchable":true,"uid":false},{"type":"string","name":"description","label":"Beschreibung","ui":{"component":"textarea"},"namespace":["page","blocks","form","description"],"searchable":true,"uid":false},{"type":"string","name":"formType","label":"Formular-Typ","required":true,"options":[{"label":"Kontaktformular (vollständig)","value":"contact"},{"label":"Schnellanfrage","value":"quick"},{"label":"Bewerbungsformular","value":"application"}],"namespace":["page","blocks","form","formType"],"searchable":true,"uid":false},{"type":"string","name":"submitButtonText","label":"Absenden-Button Text","namespace":["page","blocks","form","submitButtonText"],"searchable":true,"uid":false},{"type":"string","name":"successMessage","label":"Erfolgsmeldung","ui":{"component":"textarea"},"namespace":["page","blocks","form","successMessage"],"searchable":true,"uid":false}],"namespace":["page","blocks","form"]},{"name":"contactInfo","label":"📍 Kontaktdaten","fields":[{"type":"string","name":"title","label":"Titel","namespace":["page","blocks","contactInfo","title"],"searchable":true,"uid":false},{"type":"string","name":"description","label":"Beschreibung","ui":{"component":"textarea"},"namespace":["page","blocks","contactInfo","description"],"searchable":true,"uid":false},{"type":"object","name":"address","label":"Adresse","fields":[{"type":"string","name":"company","label":"Firmenname","required":true,"namespace":["page","blocks","contactInfo","address","company"]},{"type":"string","name":"street","label":"Straße","required":true,"namespace":["page","blocks","contactInfo","address","street"]},{"type":"string","name":"city","label":"Stadt","required":true,"namespace":["page","blocks","contactInfo","address","city"]},{"type":"string","name":"zip","label":"PLZ","required":true,"namespace":["page","blocks","contactInfo","address","zip"]}],"namespace":["page","blocks","contactInfo","address"],"searchable":true,"uid":false},{"type":"string","name":"phone","label":"Telefon","required":true,"namespace":["page","blocks","contactInfo","phone"],"searchable":true,"uid":false},{"type":"string","name":"fax","label":"Fax","namespace":["page","blocks","contactInfo","fax"],"searchable":true,"uid":false},{"type":"string","name":"email","label":"E-Mail","required":true,"namespace":["page","blocks","contactInfo","email"],"searchable":true,"uid":false},{"type":"string","name":"website","label":"Website","namespace":["page","blocks","contactInfo","website"],"searchable":true,"uid":false},{"type":"object","name":"officeHours","label":"Öffnungszeiten Büro","fields":[{"type":"string","name":"weekdays","label":"Mo-Fr Text","required":true,"namespace":["page","blocks","contactInfo","officeHours","weekdays"]}],"namespace":["page","blocks","contactInfo","officeHours"],"searchable":true,"uid":false},{"type":"object","name":"repairHours","label":"Reparaturplanung Zeiten","fields":[{"type":"string","name":"tueThu","label":"Di-Do Text","required":true,"namespace":["page","blocks","contactInfo","repairHours","tueThu"]},{"type":"string","name":"fri","label":"Fr Text","required":true,"namespace":["page","blocks","contactInfo","repairHours","fri"]}],"namespace":["page","blocks","contactInfo","repairHours"],"searchable":true,"uid":false}],"namespace":["page","blocks","contactInfo"]},{"name":"cta","label":"📣 Call-to-Action","fields":[{"type":"string","name":"eyebrow","label":"Kleine Überschrift","namespace":["page","blocks","cta","eyebrow"],"searchable":true,"uid":false},{"type":"string","name":"title","label":"Titel","namespace":["page","blocks","cta","title"],"searchable":true,"uid":false},{"type":"string","name":"description","label":"Beschreibung","ui":{"component":"textarea"},"namespace":["page","blocks","cta","description"],"searchable":true,"uid":false},{"type":"object","name":"button","label":"Button","fields":[{"type":"string","name":"text","label":"Button Text","required":true,"namespace":["page","blocks","cta","button","text"]},{"type":"string","name":"link","label":"Link","required":true,"namespace":["page","blocks","cta","button","link"]},{"type":"string","name":"variant","label":"Stil","options":[{"label":"Primär","value":"primary"},{"label":"Sekundär","value":"secondary"},{"label":"Outline","value":"outline"}],"namespace":["page","blocks","cta","button","variant"]}],"namespace":["page","blocks","cta","button"],"searchable":true,"uid":false},{"type":"string","name":"variant","label":"Stil","options":[{"label":"Dunkel","value":"dark"},{"label":"Hell","value":"light"},{"label":"Primärfarbe","value":"primary"}],"namespace":["page","blocks","cta","variant"],"searchable":true,"uid":false}],"namespace":["page","blocks","cta"]},{"name":"faq","label":"❓ FAQ","fields":[{"type":"string","name":"title","label":"Titel","namespace":["page","blocks","faq","title"],"searchable":true,"uid":false},{"type":"string","name":"description","label":"Beschreibung","namespace":["page","blocks","faq","description"],"searchable":true,"uid":false},{"type":"object","list":true,"name":"questions","label":"Fragen","ui":{"max":15},"fields":[{"type":"string","name":"question","label":"Frage","required":true,"namespace":["page","blocks","faq","questions","question"]},{"type":"string","name":"answer","label":"Antwort","ui":{"component":"textarea"},"required":true,"namespace":["page","blocks","faq","questions","answer"]}],"namespace":["page","blocks","faq","questions"],"searchable":true,"uid":false}],"namespace":["page","blocks","faq"]}],"namespace":["page","blocks"],"searchable":true,"uid":false}],"namespace":["page"]},{"name":"service","label":"🔧 Dienstleistungen","path":"content/services","format":"md","ui":{},"fields":[{"type":"string","name":"title","label":"Name der Leistung","required":true,"isTitle":true,"namespace":["service","title"],"searchable":true,"uid":false},{"type":"string","name":"subtitle","label":"Kleiner Untertitel","namespace":["service","subtitle"],"searchable":true,"uid":false},{"type":"string","name":"shortDescription","label":"Kurzbeschreibung","ui":{"component":"textarea"},"namespace":["service","shortDescription"],"searchable":true,"uid":false},{"type":"string","name":"intro","label":"Einleitungstext","ui":{"component":"textarea"},"namespace":["service","intro"],"searchable":true,"uid":false},{"type":"rich-text","name":"body","label":"Beschreibung (Lang)","namespace":["service","body"],"searchable":true,"parser":{"type":"markdown"},"uid":false},{"type":"image","name":"image","label":"Hauptbild","namespace":["service","image"],"searchable":false,"uid":false},{"type":"image","name":"heroImage","label":"Großes Titelbild","namespace":["service","heroImage"],"searchable":false,"uid":false},{"type":"string","name":"icon","label":"Icon Name (Lucide)","namespace":["service","icon"],"searchable":true,"uid":false},{"type":"string","name":"expertTip","label":"Experten-Tipp","ui":{"component":"textarea"},"namespace":["service","expertTip"],"searchable":true,"uid":false},{"type":"string","list":true,"name":"features","label":"Merkmale (Liste)","description":"Kurze Stichpunkte zu den Merkmalen dieser Leistung","namespace":["service","features"],"searchable":true,"uid":false},{"type":"string","list":true,"name":"benefits","label":"Vorteile (Liste)","description":"Kurze Stichpunkte zu den Vorteilen für den Kunden","namespace":["service","benefits"],"searchable":true,"uid":false},{"type":"object","list":true,"name":"sections","label":"Detailsektionen","description":"Ausführliche Informationsblöcke mit Icon und Text","ui":{"max":6},"fields":[{"type":"string","name":"title","label":"Titel","required":true,"namespace":["service","sections","title"],"searchable":true,"uid":false},{"type":"string","name":"icon","label":"Icon (Lucide)","description":"z.B. Hammer, Layers, CloudRain, Sun","namespace":["service","sections","icon"],"searchable":true,"uid":false},{"type":"string","name":"content","label":"Inhalt","ui":{"component":"textarea"},"namespace":["service","sections","content"],"searchable":true,"uid":false}],"namespace":["service","sections"],"searchable":true,"uid":false},{"type":"object","list":true,"name":"processSteps","label":"Prozessschritte","description":"Ablauf des Projekts in einzelnen Schritten","ui":{"max":8},"fields":[{"type":"number","name":"step","label":"Schritt Nr.","required":true,"namespace":["service","processSteps","step"],"searchable":true,"uid":false},{"type":"string","name":"title","label":"Titel","required":true,"namespace":["service","processSteps","title"],"searchable":true,"uid":false},{"type":"string","name":"text","label":"Beschreibung","ui":{"component":"textarea"},"namespace":["service","processSteps","text"],"searchable":true,"uid":false}],"namespace":["service","processSteps"],"searchable":true,"uid":false},{"type":"image","list":true,"name":"referenceImages","label":"Projektbilder","description":"Referenzbilder aus abgeschlossenen Projekten","namespace":["service","referenceImages"],"searchable":false,"uid":false},{"type":"string","list":true,"name":"contactIds","label":"Ansprechpartner IDs","description":"IDs der Team-Mitglieder (z.B. sascha, isabel)","namespace":["service","contactIds"],"searchable":true,"uid":false},{"type":"object","list":true,"name":"faq","label":"FAQ","description":"Häufig gestellte Kundenfragen","ui":{"max":10},"fields":[{"type":"string","name":"question","label":"Frage","required":true,"namespace":["service","faq","question"],"searchable":true,"uid":false},{"type":"string","name":"answer","label":"Antwort","ui":{"component":"textarea"},"required":true,"namespace":["service","faq","answer"],"searchable":true,"uid":false}],"namespace":["service","faq"],"searchable":true,"uid":false},{"type":"object","list":true,"name":"gallery","label":"Galerie","description":"Zusätzliche Bilder mit Bildunterschrift","ui":{"max":12},"fields":[{"type":"image","name":"image","label":"Bild","required":true,"namespace":["service","gallery","image"],"searchable":false,"uid":false},{"type":"string","name":"caption","label":"Bildunterschrift","namespace":["service","gallery","caption"],"searchable":true,"uid":false}],"namespace":["service","gallery"],"searchable":true,"uid":false},{"type":"object","name":"uiText","label":"🎨 UI Texte & Buttons","description":"Anpassbare Texte für Buttons und Call-to-Actions auf der Seite","fields":[{"type":"string","name":"introHeader","label":"Intro Überschrift","description":"Überschrift über dem Einleitungstext","namespace":["service","uiText","introHeader"],"searchable":true,"uid":false},{"type":"string","name":"contactButtonText","label":"Kontakt Button Text","description":"z.B. \"Kontakt aufnehmen\"","namespace":["service","uiText","contactButtonText"],"searchable":true,"uid":false},{"type":"string","name":"careerCtaTitle","label":"Karriere CTA Titel","description":"Titel der Karriere-Box","namespace":["service","uiText","careerCtaTitle"],"searchable":true,"uid":false},{"type":"string","name":"careerCtaDescription","label":"Karriere CTA Beschreibung","ui":{"component":"textarea"},"namespace":["service","uiText","careerCtaDescription"],"searchable":true,"uid":false},{"type":"string","name":"careerCtaButtonText","label":"Karriere CTA Button Text","namespace":["service","uiText","careerCtaButtonText"],"searchable":true,"uid":false}],"namespace":["service","uiText"],"searchable":true,"uid":false}],"namespace":["service"]},{"name":"job","label":"📋 Stellenangebote","path":"content/jobs","format":"md","ui":{},"fields":[{"type":"string","name":"title","label":"Jobtitel","required":true,"isTitle":true,"namespace":["job","title"],"searchable":true,"uid":false},{"type":"string","name":"location","label":"Standort","required":true,"namespace":["job","location"],"searchable":true,"uid":false},{"type":"string","name":"type","label":"Anstellungsart","required":true,"options":["Vollzeit","Teilzeit","Ausbildung"],"namespace":["job","type"],"searchable":true,"uid":false},{"type":"string","name":"shortDesc","label":"Kurzbeschreibung","ui":{"component":"textarea"},"namespace":["job","shortDesc"],"searchable":true,"uid":false},{"type":"string","list":true,"name":"tasks","label":"Aufgaben","namespace":["job","tasks"],"searchable":true,"uid":false},{"type":"string","list":true,"name":"profile","label":"Ihr Profil","namespace":["job","profile"],"searchable":true,"uid":false},{"type":"string","list":true,"name":"benefits","label":"Wir bieten","namespace":["job","benefits"],"searchable":true,"uid":false},{"type":"boolean","name":"published","label":"Veröffentlicht?","namespace":["job","published"],"searchable":true,"uid":false}],"namespace":["job"]},{"name":"teamMember","label":"👥 Team","path":"content/team","format":"md","ui":{},"fields":[{"type":"string","name":"name","label":"Vor- & Nachname","required":true,"isTitle":true,"namespace":["teamMember","name"],"searchable":true,"uid":false},{"type":"string","name":"role","label":"Position / Jobtitel","required":true,"namespace":["teamMember","role"],"searchable":true,"uid":false},{"type":"string","name":"email","label":"E-Mail","namespace":["teamMember","email"],"searchable":true,"uid":false},{"type":"string","name":"category","label":"Abteilung","required":true,"options":[{"label":"Geschäftsführung","value":"leadership"},{"label":"Büro","value":"office"},{"label":"Dachdecker","value":"craftsmen"}],"namespace":["teamMember","category"],"searchable":true,"uid":false},{"type":"string","name":"description","label":"Beschreibung","ui":{"component":"textarea"},"namespace":["teamMember","description"],"searchable":true,"uid":false},{"type":"image","name":"image","label":"Foto","namespace":["teamMember","image"],"searchable":false,"uid":false},{"type":"number","name":"order","label":"Reihenfolge","namespace":["teamMember","order"],"searchable":true,"uid":false}],"namespace":["teamMember"]},{"name":"settings","label":"⚙️ Einstellungen","path":"content/globals","format":"json","match":{"include":"settings"},"ui":{"global":true,"allowedActions":{"create":false,"delete":false}},"fields":[{"type":"string","name":"siteName","label":"Website Name","required":true,"namespace":["settings","siteName"],"searchable":true,"uid":false},{"type":"string","name":"siteDescription","label":"Website Beschreibung","namespace":["settings","siteDescription"],"searchable":true,"uid":false},{"type":"image","name":"favicon","label":"Favicon","namespace":["settings","favicon"],"searchable":false,"uid":false},{"type":"image","name":"logo","label":"Logo","namespace":["settings","logo"],"searchable":false,"uid":false},{"type":"image","name":"defaultOgImage","label":"Standard Social Bild","namespace":["settings","defaultOgImage"],"searchable":false,"uid":false},{"type":"string","name":"gtmId","label":"Google Tag Manager ID","namespace":["settings","gtmId"],"searchable":true,"uid":false},{"type":"string","name":"gaId","label":"Google Analytics ID","namespace":["settings","gaId"],"searchable":true,"uid":false},{"type":"string","name":"sentryDsn","label":"Sentry DSN","namespace":["settings","sentryDsn"],"searchable":true,"uid":false},{"type":"object","name":"cookieBanner","label":"🍪 Cookie Banner","fields":[{"type":"string","name":"message","label":"Text","ui":{"component":"textarea"},"namespace":["settings","cookieBanner","message"],"searchable":true,"uid":false},{"type":"string","name":"privacyLinkText","label":"Datenschutz Link Text","namespace":["settings","cookieBanner","privacyLinkText"],"searchable":true,"uid":false},{"type":"string","name":"cookieLinkText","label":"Cookie-Einstellungen Link Text","namespace":["settings","cookieBanner","cookieLinkText"],"searchable":true,"uid":false},{"type":"string","name":"rejectButtonText","label":"Ablehnen Button Text","namespace":["settings","cookieBanner","rejectButtonText"],"searchable":true,"uid":false},{"type":"string","name":"acceptButtonText","label":"Annehmen Button Text","namespace":["settings","cookieBanner","acceptButtonText"],"searchable":true,"uid":false}],"namespace":["settings","cookieBanner"],"searchable":true,"uid":false},{"type":"object","name":"notFoundPage","label":"🔍 404 Seite","fields":[{"type":"string","name":"title","label":"Titel","required":true,"namespace":["settings","notFoundPage","title"],"searchable":true,"uid":false},{"type":"string","name":"description","label":"Beschreibung","ui":{"component":"textarea"},"namespace":["settings","notFoundPage","description"],"searchable":true,"uid":false},{"type":"string","name":"buttonText","label":"Button Text","namespace":["settings","notFoundPage","buttonText"],"searchable":true,"uid":false}],"namespace":["settings","notFoundPage"],"searchable":true,"uid":false}],"namespace":["settings"]},{"name":"navigation","label":"🧭 Menü","path":"content/globals","format":"json","match":{"include":"navigation"},"ui":{"global":true,"allowedActions":{"create":false,"delete":false}},"fields":[{"type":"image","name":"logo","label":"Logo","namespace":["navigation","logo"],"searchable":false,"uid":false},{"type":"object","name":"ctaButton","label":"Button oben rechts","fields":[{"type":"string","name":"text","label":"Text","required":true,"namespace":["navigation","ctaButton","text"],"searchable":true,"uid":false},{"type":"string","name":"link","label":"Link","required":true,"namespace":["navigation","ctaButton","link"],"searchable":true,"uid":false}],"namespace":["navigation","ctaButton"],"searchable":true,"uid":false},{"type":"object","list":true,"name":"items","label":"Menüpunkte","ui":{},"fields":[{"type":"string","name":"label","label":"Name (z.B. Leistungen)","required":true,"namespace":["navigation","items","label"],"searchable":true,"uid":false},{"type":"string","name":"href","label":"Link (z.B. /services)","required":true,"namespace":["navigation","items","href"],"searchable":true,"uid":false}],"namespace":["navigation","items"],"searchable":true,"uid":false}],"namespace":["navigation"]},{"name":"footer","label":"🦶 Footer","path":"content/globals","format":"json","match":{"include":"footer"},"ui":{"global":true,"allowedActions":{"create":false,"delete":false}},"fields":[{"type":"string","name":"copyright","label":"Copyright Text","namespace":["footer","copyright"],"searchable":true,"uid":false},{"type":"object","list":true,"name":"links","label":"Links","fields":[{"type":"string","name":"label","label":"Bezeichnung","required":true,"namespace":["footer","links","label"],"searchable":true,"uid":false},{"type":"string","name":"href","label":"Link","required":true,"namespace":["footer","links","href"],"searchable":true,"uid":false}],"namespace":["footer","links"],"searchable":true,"uid":false},{"type":"object","list":true,"name":"social","label":"Social Media","fields":[{"type":"string","name":"platform","label":"Plattform","required":true,"namespace":["footer","social","platform"],"searchable":true,"uid":false},{"type":"string","name":"url","label":"URL","required":true,"namespace":["footer","social","url"],"searchable":true,"uid":false}],"namespace":["footer","social"],"searchable":true,"uid":false}],"namespace":["footer"]},{"name":"legalPage","label":"⚖️ Rechtstexte","path":"content/legal","format":"md","ui":{},"fields":[{"type":"string","name":"title","label":"Seitentitel (Intern)","required":true,"isTitle":true,"namespace":["legalPage","title"],"searchable":true,"uid":false},{"type":"object","name":"seo","label":"🔍 SEO & Google","fields":[{"type":"string","name":"title","label":"Browser-Titel","required":true,"description":"Titel im Browser-Tab","namespace":["legalPage","seo","title"],"searchable":true,"uid":false},{"type":"string","name":"description","label":"Suchbeschreibung","ui":{"component":"textarea"},"description":"Text in Google-Ergebnissen","namespace":["legalPage","seo","description"],"searchable":true,"uid":false},{"type":"image","name":"ogImage","label":"Social Media Bild","description":"Bild für Facebook/Twitter Vorschau","namespace":["legalPage","seo","ogImage"],"searchable":false,"uid":false}],"namespace":["legalPage","seo"],"searchable":true,"uid":false},{"type":"rich-text","name":"body","label":"Inhalt","isBody":true,"namespace":["legalPage","body"],"searchable":true,"parser":{"type":"markdown"},"uid":false}],"namespace":["legalPage"]}],"config":{"media":{"tina":{"publicFolder":"public","mediaRoot":"uploads"}}}}